Metadata-Version: 1.0
Name: dsnd-probability-beta
Version: 0.1
Summary: Gaussian and Binomial distributions
Home-page: UNKNOWN
Author: bhadresh savani
Author-email: bhadreshpsavani@gmail.com
License: UNKNOWN
Platform: UNKNOWN
